coinexlib/__init__.py
coinexlib/coinexLib.py
coinexlib-1.1.0.dist-info/METADATA
coinexlib-1.1.0.dist-info/WHEEL
coinexlib-1.1.0.dist-info/top_level.txt
coinexlib-1.1.0.dist-info/RECORD
