Metadata-Version: 2.1
Name: coinexlib
Version: 1.1.0
Summary: A Python library for interacting with the CoinEx API.
Home-page: https://github.com/reza9898/coinexlib
Author: Reza Rizvandi
Author-email: r.rizvandi@gmail.com
Classifier: Programming Language :: Python :: 3
Classifier: License :: OSI Approved :: MIT License
Classifier: Operating System :: OS Independent
Requires-Python: >=3.6
Requires-Dist: requests
